belenios/__init__.py
belenios/main.py
belenios/config/__init__.py
belenios/config/config.py
belenios/controllers/__init__.py
belenios/controllers/default_cmd.py
belenios/controllers/election_cmd.py
belenios/controllers/setup_cmd.py
belenios/core/__init__.py
belenios/core/belenios/CredentialAuthorityCore.py
belenios/core/belenios/ServerAdministratorCore.py
belenios/core/belenios/ServerCore.py
belenios/core/belenios/TrusteeCore.py
belenios/core/belenios/VoterCore.py
belenios/core/belenios/__init__.py
belenios/core/command_line/__init__.py
belenios/core/command_line/exc.py
belenios/core/command_line/version.py
belenios/custom_types/__init__.py
belenios/custom_types/belenios/ArrayOfGsType.py
belenios/custom_types/belenios/ArrayOfIsType.py
belenios/custom_types/belenios/ArrayOfStringsType.py
belenios/custom_types/belenios/BType.py
belenios/custom_types/belenios/EventType.py
belenios/custom_types/belenios/GType.py
belenios/custom_types/belenios/HType.py
belenios/custom_types/belenios/IType.py
belenios/custom_types/belenios/NType.py
belenios/custom_types/belenios/PrivateKeyType.py
belenios/custom_types/belenios/PublicKeyType.py
belenios/custom_types/belenios/StringType.py
belenios/custom_types/belenios/UuidType.py
belenios/custom_types/belenios/ZqType.py
belenios/custom_types/belenios/__init__.py
belenios/custom_types/command_line/RoleType.py
belenios/custom_types/command_line/__init__.py
belenios/dataclass/__init__.py
belenios/dataclass/dataclass.py
belenios/models/BaseModel.py
belenios/models/__init__.py
belenios/models/belenios/AnswerHModel.py
belenios/models/belenios/AnswerModel.py
belenios/models/belenios/AnswerNhModel.py
belenios/models/belenios/BallotModel.py
belenios/models/belenios/CertKeysModel.py
belenios/models/belenios/ChannelMsgModel.py
belenios/models/belenios/CiphertextModel.py
belenios/models/belenios/CredentialModel.py
belenios/models/belenios/DecryptionFactorRowModel.py
belenios/models/belenios/DecryptionProofRowModel.py
belenios-0.0.4.dist-info/LICENSE.md
belenios-0.0.4.dist-info/METADATA
belenios-0.0.4.dist-info/WHEEL
belenios-0.0.4.dist-info/entry_points.txt
belenios-0.0.4.dist-info/top_level.txt
belenios-0.0.4.dist-info/RECORD
