Metadata-Version: 2.1
Name: belenios
Version: 0.0.4
Summary: This is a proof of concept of the Belenios election protocol.
Home-page: https://etulab.univ-amu.fr/b21211803/projet-ter-2024-belenios
Author: BISCHOFF Taylor, BRIONGOS Alexandre, ILLA Mohamed abdallahi, MALIGUE Dylan
Author-email: alexandre.briongos@etu.univ-amu.fr
License: unlicensed
License-File: LICENSE.md
Requires-Dist: cement[colorlog,jinja2,yaml] ==3.0.8
Requires-Dist: SQLAlchemy ==2.0.25
Requires-Dist: pycryptodome ==3.20.0
Requires-Dist: base58 ==2.1.1
